lyrics_converter/__about__.py
lyrics_converter/__init__.py
lyrics_converter/cli.py
lyrics_converter/converter.py
lyrics_converter-0.2.1.dist-info/METADATA
lyrics_converter-0.2.1.dist-info/WHEEL
lyrics_converter-0.2.1.dist-info/entry_points.txt
lyrics_converter-0.2.1.dist-info/licenses/LICENSE.txt
lyrics_converter-0.2.1.dist-info/RECORD
