Metadata-Version: 2.3
Name: lyrics-converter
Version: 0.2.1
Summary: Tool to convert between different text-based lyrics formats (e.g. LRC, MidiCo LRC, ASS, TXT)
Project-URL: Documentation, https://github.com/beveradb/lyrics-converter#readme
Project-URL: Issues, https://github.com/beveradb/lyrics-converter/issues
Project-URL: Source, https://github.com/beveradb/lyrics-converter
Project-URL: Homepage, https://github.com/beveradb/lyrics-converter
Author-email: Andrew Beveridge <andrew@beveridge.uk>
License-Expression: MIT
License-File: LICENSE.txt
Classifier: Development Status :: 4 - Beta
Classifier: Programming Language :: Python
Classifier: Programming Language :: Python :: 3.10
Classifier: Programming Language :: Python :: 3.11
Classifier: Programming Language :: Python :: 3.12
Classifier: Programming Language :: Python :: Implementation :: CPython
Classifier: Programming Language :: Python :: Implementation :: PyPy
Requires-Python: >=3.10
